milli_piyango/__init__.py
milli_piyango/milli_piyango.py
milli_piyango-1.1.0.dist-info/METADATA
milli_piyango-1.1.0.dist-info/RECORD
milli_piyango-1.1.0.dist-info/WHEEL
milli_piyango-1.1.0.dist-info/top_level.txt
