Metadata-Version: 2.1
Name: milli-piyango
Version: 1.1.0
Summary: A package for getting lottery data from mpi.gov.tr(Turkish Lottery)
Home-page: https://github.com/molcay/milli-piyango
Author: M. Olcay TERCANLI
Author-email: molcaytercanli@gmail.com
License: UNKNOWN
Platform: UNKNOWN
Classifier: Programming Language :: Python :: 3.6
Classifier: License :: OSI Approved :: MIT License
Classifier: Operating System :: OS Independent
Requires-Dist: requests
